relational_datasets/__init__.py
relational_datasets/_base.py
relational_datasets/_version.py
relational_datasets/request.py
relational_datasets/types.py
relational_datasets/convert/__init__.py
relational_datasets/convert/convert_numpy.py
relational_datasets/convert/tests/__init__.py
relational_datasets/convert/tests/test_convert_numpy.py
relational_datasets/tests/__init__.py
relational_datasets/tests/test_base.py
relational_datasets/tests/test_load.py
relational_datasets-0.4.0.dist-info/LICENSE
relational_datasets-0.4.0.dist-info/METADATA
relational_datasets-0.4.0.dist-info/WHEEL
relational_datasets-0.4.0.dist-info/top_level.txt
relational_datasets-0.4.0.dist-info/RECORD
