Metadata-Version: 2.1
Name: relational-datasets
Version: 0.4.0
Summary: A small library for loading and downloading relational datasets
Home-page: https://srlearn.github.io/relational-datasets/
Download-URL: https://pypi.org/project/relational-datasets/
Author: Alexander L. Hayes
Author-email: alexander@batflyer.net
License: Apache License, Version 2.0
Project-URL: Bug Tracker, https://github.com/srlearn/relational-datasets/issues
Project-URL: Documentation, https://srlearn.github.io/relational-datasets/
Project-URL: Source Code, https://github.com/srlearn/relational-datasets/
Classifier: License :: OSI Approved :: Apache Software License
Classifier: Development Status :: 4 - Beta
Classifier: Topic :: Scientific/Engineering :: Artificial Intelligence
Requires-Python: >=3.7
License-File: LICENSE
